{"contract":"shard-readiness.v1","evidenceType":"shard_readiness","project":"mini-kv","version":"0.102.0","releaseVersion":"v146","readOnly":true,"executionAllowed":false,"shardEnabled":false,"shardCount":1,"slotCount":16,"routingMode":"single-shard-readiness-prototype","evidencePath":"fixtures/release/shard-readiness.json","status":"historical-fallback-hardened-read-only","shardMap":[{"shardId":"shard-0","slotStart":0,"slotEnd":15,"storagePath":"not-created","readOnly":true,"writesAllowed":false}],"keyRoutingSamples":[{"key":"orderops:alpha","slot":5,"shardId":"shard-0"},{"key":"audit:receipt:001","slot":9,"shardId":"shard-0"},{"key":"mini-kv:health","slot":14,"shardId":"shard-0"}],"boundaries":{"orderAuthoritative":false,"auditAuthoritative":false,"writeCommandsAllowed":false,"adminCommandsAllowed":false,"loadRestoreCompactAllowed":false,"setnxexExecutionAllowed":false,"multiProcessStarted":false,"storageDirectoriesCreated":false,"activeRouterInstalled":false,"archivedNodeEvidenceMutated":false},"diagnostics":{"writeCommandsExecuted":false,"adminCommandsExecuted":false,"loadRestoreCompactExecuted":false,"nodeConsumer":"Node v378+ may consume v146 after Node v377 archive verification","javaEchoExpected":"Java shard-readiness echo may consume the same shard-readiness.v1 fields","nodeArchivedEvidencePreserved":true},"commandCatalog":{"command":"SHARDJSON","category":"read","mutatesStore":false,"touchesWal":false,"stable":true,"extraArgsAllowed":false,"sideEffects":["metadata_read"]},"fixtureParity":{"currentFixturePath":"fixtures/release/shard-readiness.json","historicalFixturePaths":["fixtures/release/shard-readiness-v144.json","fixtures/release/shard-readiness-v145.json"],"runtimeMatchesCurrentFixture":true,"historicalFixturesPreserved":true},"archiveCompatibility":{"preservesNodeArchivedEvidence":true,"archivedNodeVersions":["Node v370","Node v371","Node v372","Node v373","Node v374","Node v375","Node v376"],"changesArchivedNodeEvidence":false,"futureNodeConsumer":"Node v378 or later after v377 archive verification"},"historicalFallback":{"previousConsumedReleaseVersion":"v145","previousConsumedFixturePath":"fixtures/release/shard-readiness-v145.json","olderPrototypeFixturePath":"fixtures/release/shard-readiness-v144.json","rollingCurrentUsedForHistoricalBaseline":false,"nodeV376ConsumptionPreserved":true,"nodeV377ReadsUnfinishedUpstream":false},"readOnlyBoundaryFields":["readOnly","executionAllowed","boundaries.writeCommandsAllowed","boundaries.adminCommandsAllowed","boundaries.loadRestoreCompactAllowed","boundaries.archivedNodeEvidenceMutated","archiveCompatibility.changesArchivedNodeEvidence","historicalFallback.rollingCurrentUsedForHistoricalBaseline"],"evidenceDigest":"fnv1a64:6847d87decb76fcb","notes":["read-only shard readiness hardening","single logical shard only","slot table is evidence, not active storage routing","does not create shard directories or start extra processes","freezes v145 evidence for historical fallback","does not mutate Node v370-v376 archived evidence","not order or audit authoritative"]}
